conqur/__init__.py
conqur/conqur.py
conqur/scaler.py
conqur-1.0.0.dist-info/AUTHORS.rst
conqur-1.0.0.dist-info/LICENSE
conqur-1.0.0.dist-info/METADATA
conqur-1.0.0.dist-info/WHEEL
conqur-1.0.0.dist-info/top_level.txt
conqur-1.0.0.dist-info/RECORD
