Metadata-Version: 2.1
Name: conqur
Version: 1.0.0
Summary: Batch effects removal for microbiome data via conditional quantile regression on Python
Home-page: https://github.com/quantori/conqur
Author: Aleksandr Grefenstein
Author-email: alexander.grefenshteyn@quantori.com
License: MIT license
Keywords: conqur
Platform: UNKNOWN
Classifier: Development Status :: 5 - Production/Stable
Classifier: Intended Audience :: Developers
Classifier: License :: OSI Approved :: MIT License
Classifier: Natural Language :: English
Classifier: Programming Language :: Python :: 3
Classifier: Programming Language :: Python :: 3.7
Classifier: Programming Language :: Python :: 3.8
Classifier: Programming Language :: Python :: 3.9
Requires-Python: >=3.7
License-File: LICENSE
License-File: AUTHORS.rst
Requires-Dist: numpy (>=1.21.6)
Requires-Dist: scikit-learn (>=1.0.2)
Requires-Dist: setuptools (>=60.2.0)
Provides-Extra: test
Requires-Dist: pandas (>=1.3.0) ; extra == 'test'
